fastapi_performance_monitor/__init__.py
fastapi_performance_monitor/metrics.py
fastapi_performance_monitor/middleware.py
fastapi_performance_monitor/router.py
fastapi_performance_monitor/static/index.html
fastapi_performance_monitor-0.1.3.dist-info/licenses/LICENSE
fastapi_performance_monitor-0.1.3.dist-info/METADATA
fastapi_performance_monitor-0.1.3.dist-info/WHEEL
fastapi_performance_monitor-0.1.3.dist-info/top_level.txt
fastapi_performance_monitor-0.1.3.dist-info/RECORD
