Metadata-Version: 2.4
Name: fastapi-performance-monitor
Version: 0.1.3
Summary: A plug-and-play performance monitoring tool for FastAPI with a real-time dashboard.
Author-email: Parham Davari <parham.davarii@gmail.com>
Project-URL: Homepage, https://github.com/parhamdavari/fastapi-performance-monitor
Project-URL: Bug Tracker, https://github.com/parhamdavari/fastapi-performance-monitor/issues
Classifier: Programming Language :: Python :: 3
Classifier: License :: OSI Approved :: MIT License
Classifier: Operating System :: OS Independent
Classifier: Framework :: FastAPI
Requires-Python: >=3.8
License-File: LICENSE
Requires-Dist: fastapi
Provides-Extra: test
Requires-Dist: pytest>=7.0.0; extra == "test"
Requires-Dist: pytest-cov>=4.0.0; extra == "test"
Requires-Dist: pytest-asyncio>=0.18.0; extra == "test"
Requires-Dist: httpx>=0.23.0; extra == "test"
Requires-Dist: numpy>=1.20.0; extra == "test"
Provides-Extra: dev
Requires-Dist: uvicorn; extra == "dev"
Dynamic: license-file
